README.rst
setup.py
Pyoko.egg-info/PKG-INFO
Pyoko.egg-info/SOURCES.txt
Pyoko.egg-info/dependency_links.txt
Pyoko.egg-info/requires.txt
Pyoko.egg-info/top_level.txt
pyoko/__init__.py
pyoko/conf.py
pyoko/exceptions.py
pyoko/fields.py
pyoko/listnode.py
pyoko/manage.py
pyoko/model.py
pyoko/modelmeta.py
pyoko/node.py
pyoko/registry.py
pyoko/settings.py
pyoko/db/__init__.py
pyoko/db/connection.py
pyoko/db/queryset.py
pyoko/db/schema_update.py
pyoko/db/solr_schema_template.xml
pyoko/db/adapter/__init__.py
pyoko/db/adapter/base.py
pyoko/db/adapter/db_riak.py
pyoko/lib/__init__.py
pyoko/lib/py2map.py
pyoko/lib/utils.py