Metadata-Version: 1.1
Name: Pyoko
Version: 0.9.3
Summary: Pyoko is a Django-esque ORM for Riak KV
Home-page: https://github.com/zetaops/pyoko
Author: Zetaops AS
Author-email: info@zetaops.io
License: GPL v3
Keywords: riak,orm,database,nosql
Platform: UNKNOWN
Requires: enum34
Requires: six
Requires: riak
Requires: lazy_object_proxy
